chift_mcp/__init__.py
chift_mcp/__main__.py
chift_mcp/config.py
chift_mcp/constants.py
chift_mcp/http_client.py
chift_mcp/middleware.py
chift_mcp/prompts.py
chift_mcp/proxy.py
chift_mcp/route_maps.py
chift_mcp/server.py
chift_mcp/tools.py
chift_mcp/utils/__init__.py
chift_mcp/utils/tool_factory.py
chift_mcp/utils/utils.py
chift_mcp_server-0.2.4.dist-info/METADATA
chift_mcp_server-0.2.4.dist-info/WHEEL
chift_mcp_server-0.2.4.dist-info/entry_points.txt
chift_mcp_server-0.2.4.dist-info/RECORD
