Metadata-Version: 2.4
Name: chift-mcp-server
Version: 0.2.4
Summary: MCP Server to interact with Chift API via Chift Python SDK
Author-email: Dima Redchyts <dima.redchyts@chift.eu>
License-Expression: MIT
Requires-Python: <4.0,>=3.11
Requires-Dist: chift==0.3.11
Requires-Dist: fastmcp>=2.12.0
Requires-Dist: inflect>=7.5.0
Requires-Dist: loguru>=0.7.3
Requires-Dist: mcp>=1.12.4
Requires-Dist: mcp[cli]==1.12.4
Requires-Dist: pydantic-config>=0.3.0
Requires-Dist: pydantic>=2.11.7
